README.md
setup.cfg
setup.py
gcp_secrets_kube/__init__.py
gcp_secrets_kube/main.py
gcp_secrets_kube.egg-info/PKG-INFO
gcp_secrets_kube.egg-info/SOURCES.txt
gcp_secrets_kube.egg-info/dependency_links.txt
gcp_secrets_kube.egg-info/entry_points.txt
gcp_secrets_kube.egg-info/requires.txt
gcp_secrets_kube.egg-info/top_level.txt