Metadata-Version: 1.1
Name: gcp-secrets-kube
Version: 0.1
Summary: UNKNOWN
Home-page: https://github.com/pymentor-fr/gcp-secrets-kube
Author: mike
Author-email: mike@pymentor.fr
License: UNKNOWN
Download-URL: https://github.com/pymentor-fr/gcp-secrets-kube/archive/v0.1.0.tar.gz
Platform: UNKNOWN
